{ "Id": "skill_rollo_dunpai_feibiao", "Name": "盾牌飞掷", "Type": "active", "Trigger": "", "Costs": [ { "Card": "A", "Count": 1 }, { "Card": "D", "Count": 1 } ], "Targeting": { "TargetType": "enemy", "Range": 2, "RangeShape": "distance_and_adjacent_bounce", "Movement": "" }, "Description": "使用 A + D 依次对距离 2 内的敌方目标及其相邻的 1 个目标分别造成 1 点物理伤害。若本次攻击未造成伤害，且未放置 D，可获得本次攻击用的 D，并立刻放置此 D。", "Effects": [], "Options": [], "Metadata": { "Version": 1, "CreatedAt": "2026-06-18T00:00:00", "UpdatedAt": "2026-06-18T00:00:00", "Tags": [ "物理", "范围", "盾" ] } }
